marienbad/__init__.py
marienbad/generator.py
marienbad/solver.py
marienbad-0.1.2.1.dist-info/LICENSE
marienbad-0.1.2.1.dist-info/METADATA
marienbad-0.1.2.1.dist-info/WHEEL
marienbad-0.1.2.1.dist-info/entry_points.txt
marienbad-0.1.2.1.dist-info/top_level.txt
marienbad-0.1.2.1.dist-info/RECORD
