Metadata-Version: 2.1
Name: marienbad
Version: 0.1.2.1
Summary: A toolsuite for win at Marienbad (Nim) game.
Author-email: alberic89 <alberic89@gmx.com>
Project-URL: Homepage, https://github.com/alberic89/Mathenjeans2022/tree/main/marienbad
Project-URL: Bug Tracker, https://github.com/alberic89/Mathenjeans2022/issues
Keywords: Marienbad,Nim
Classifier: Programming Language :: Python :: 3
Classifier: License :: OSI Approved :: GNU General Public License v3 (GPLv3)
Classifier: Operating System :: OS Independent
Classifier: Topic :: Games/Entertainment
Classifier: Natural Language :: French
Requires-Python: >=3
License-File: LICENSE
